{
  "temperature": 0.9,
  "downfall": 0.5,
  "has_precipitation": true,
  "effects": {
    "fog_color": 255,
    "water_color": 255,
    "water_fog_color": 255,
    "sky_color": 255
  },
  "spawners": {
    "monster": [],
    "creature": [
      {
        "type": "minecraft:parrot",
        "weight": 10,
        "minCount": 1,
        "maxCount": 4
      }
    ],
    "ambient": [],
    "water_creature": [],
    "water_ambient": []
  },
  "features": [
    [],
    [],
    [],
    [],
    [],
    [],
    [],
    [],
    [],
    [],
    []
  ]
}